{
  "header": {
    "title": "Encontro de Divulgação de Resultados – Gondim | 2026 (EDR)",
    "subtitle": "Período acumulado: fev e mar/26",
    "band": "DATA DE DIVULGAÇÃO: 22 DE MAIO DE 2026"
  },
  "revenue_mix": {
    "icon": "💰",
    "title": "Estrutura de Receita",
    "value": 8319716.223999999,
    "contratual": 7364623.933999999,
    "sucumbencia": 901990.29,
    "outras": 53102.0,
    "outras_receitas": 53102.0,
    "pct_contratual": 0.8852013380883313,
    "pct_sucumbencia": 0.10841599229046013,
    "pct_outras": 0.006382669621208465,
    "pct_orcado": 0.9192233107791995,
    "receita_orcada": 54304864.5075,
    "meta_periodo_receita": 9050810.75125,
    "meta_periodo_meses": 2,
    "receita_2025_periodo": 9072350.655208666,
    "variacao_yoy": -0.08295914254334515,
    "subtitle": "",
    "comparison_pct": -8.295914254334514,
    "rows": [
      {
        "label": "Contratuais",
        "value": "R$ 7,36 M",
        "share": "88,5%"
      },
      {
        "label": "Sucumbência",
        "value": "R$ 902 mil",
        "share": "10,8%"
      },
      {
        "label": "Outras Receitas",
        "value": "R$ 53,1 mil",
        "share": "0,6%"
      }
    ],
    "expansions": [
      {
        "title": "Contratuais",
        "items": [
          {
            "name": "SANTANDER",
            "value": "R$ 1,03 M"
          },
          {
            "name": "SANEAMENTO",
            "value": "R$ 981,1 mil"
          },
          {
            "name": "MRS",
            "value": "R$ 958,2 mil"
          },
          {
            "name": "RECUPERA",
            "value": "R$ 894,4 mil"
          },
          {
            "name": "MERCADO LIVRE",
            "value": "R$ 734,9 mil"
          }
        ]
      },
      {
        "title": "Sucumbência",
        "items": []
      }
    ],
    "receita_orcada_anual": 54304864.5075,
    "variacao_2025": -0.08295914254334515
  },
  "cost_structure": {
    "icon": "📉",
    "title": "Estrutura de Custos",
    "total": 4179964.483385101,
    "correspondentes": 250137.57773399996,
    "outras_despesas": 608692.7470196874,
    "impostos": 1558889.4986314136,
    "socios_servico": 1544357.73,
    "clt": 217886.93,
    "cost_total_anterior": 5577491.672544276,
    "variacao_custos_yoy": -0.2505655357655904,
    "value": "R$ 4,18 M",
    "subtitle": "+10,9% vs 2025",
    "highlight": {
      "label": "Impostos",
      "value": "37,3%",
      "caption": "principal grupo de custo"
    },
    "items": [
      {
        "label": "Impostos",
        "value": "R$ 1,56 M",
        "share": "37,3%",
        "details": []
      },
      {
        "label": "Sócios de Serviço",
        "value": "R$ 1,54 M",
        "share": "36,9%",
        "details": []
      },
      {
        "label": "CLT",
        "value": "R$ 217,9 mil",
        "share": "5,2%",
        "details": []
      },
      {
        "label": "Correspondentes",
        "value": "R$ 250,1 mil",
        "share": "6,0%",
        "details": []
      },
      {
        "label": "Outras Despesas",
        "value": "R$ 608,7 mil",
        "share": "14,6%",
        "details": []
      }
    ],
    "cost_subtitle": "+10,9% vs 2025",
    "custo_orcado_anual": 28243188.09342022,
    "meta_periodo_custos": 4707198.015570036,
    "meta_periodo_meses": 2,
    "pct_orcado_custos": 0.8879941888059519,
    "variacao_2025": 0.10927291716090819
  },
  "net_result": {
    "icon": "📊",
    "title": "Resultado Líquido",
    "value": 747725.0339555574,
    "subtitle": "",
    "sem_sucumbencia": 91485.57874055719,
    "resultado_orcado_anual": 4820666.95567322,
    "resultado_orcado": 803444.4926122032,
    "meta_periodo_resultado": 803444.4926122032,
    "meta_periodo_meses": 2,
    "resultado_2025": 1308363.6476702648,
    "pct_vs_orcado": 0.9306492742572824,
    "variacao_2025": -0.4285036615875162,
    "pct_ano": 0.15510821237621372,
    "resultado_operacional": 5698641.2392463125
  },
  "margins": {
    "icon": "📈",
    "title": "Margens",
    "value": "27,6%",
    "subtitle": "",
    "metrics": [
      {
        "label": "Margem Operacional",
        "value": "27,6%",
        "caption": ""
      },
      {
        "label": "Margem Líquida",
        "value": "5,8%",
        "caption": ""
      }
    ]
  },
  "people": {
    "icon": "👥",
    "title": "Pessoas",
    "value": "602",
    "total": 602,
    "socios": {
      "qtd": 441,
      "pct": 0.7325581395348837
    },
    "clt": {
      "qtd": 124,
      "pct": 0.2059800664451827
    },
    "estagiarios": {
      "qtd": 37,
      "pct": 0.061461794019933555
    },
    "subtitle": "",
    "rows": [
      {
        "label": "Sócios de Serviço",
        "value": "441",
        "share": "73,3%"
      },
      {
        "label": "CLT",
        "value": "124",
        "share": "20,6%"
      },
      {
        "label": "Estagiários",
        "value": "37",
        "share": "6,1%"
      }
    ]
  },
  "top_clients": {
    "icon": "🏆",
    "title": "Top 5 Clientes",
    "subtitle": "Faturamento em fev e mar/26",
    "ranking": [
      {
        "name": "SANTANDER",
        "value": "R$ 1,03 M"
      },
      {
        "name": "SANEAMENTO",
        "value": "R$ 981,1 mil"
      },
      {
        "name": "MRS",
        "value": "R$ 958,2 mil"
      },
      {
        "name": "RECUPERA",
        "value": "R$ 894,4 mil"
      },
      {
        "name": "MERCADO LIVRE",
        "value": "R$ 734,9 mil"
      },
      {
        "name": "Outros",
        "value": "R$ 3,69 M"
      }
    ]
  },
  "insights": [
    {
      "tone": "red",
      "title": "Efeito tesoura",
      "description": "Receita e custos seguem em direções distintas, mas ainda preservam resultado operacional de R$ 4,14 M."
    },
    {
      "tone": "yellow",
      "title": "Sócios de Serviço concentra 36,9%",
      "description": "A linha de Sócios de Serviço soma R$ 1,54 M e segue como eixo prioritário de produtividade e revisão de eficiência."
    },
    {
      "tone": "green",
      "title": "Estrutura de pessoas",
      "description": "A base segue concentrada em pessoas, com Sócios de Serviço 73,3%, CLT 20,6%, Estagiários 6,1%, o que reforça uma estrutura mais rígida no curto prazo."
    },
    {
      "tone": "blue",
      "title": "Top 5 clientes",
      "description": "SANTANDER lidera um grupo que soma R$ 8,29 M e mantém concentração moderada na frente comercial."
    }
  ],
  "technical_analysis": {
    "title": "Análise técnica",
    "paragraphs": [
      "No acumulado do período, a receita somou R$ 8,32 M e a estrutura de custos atingiu R$ 4,18 M, produzindo resultado operacional positivo de R$ 4,14 M. O ritmo entre receita e despesas segue relativamente equilibrado.",
      "A comparação interanual de período acumulado: fev e mar/26 deve ser lida com cautela, mas já evidencia um descolamento relevante entre receita e custos. Como o painel observa um recorte parcial do ano, o efeito de base, sazonalidade e timing de reconhecimento das linhas pode ampliar ou suavizar a fotografia do período.",
      "Mesmo sem considerar a sucumbência, o resultado líquido permaneceria em R$ 0, sugerindo que a geração recorrente ainda se sustenta com menor dependência de receitas extraordinárias.",
      "O principal vetor de rigidez está na estrutura de pessoas: o desembolso com essa frente responde por 42,1% do total de custos, patamar moderado. Em paralelo, a linha de Sócios de Serviço concentra 36,9%, o que reforça a necessidade de disciplina sobre capacidade, alocação e produtividade.",
      "Na camada complementar, correspondentes somam R$ 250,1 mil (6,0%) e outras despesas atingem R$ 608,7 mil (14,6%). Juntas, essas rubricas representam R$ 858,8 mil e 20,6% dos custos, oferecendo espaço para ajustes táticos sem alterar a espinha dorsal da operação.",
      "Na frente comercial, o faturamento segue concentrado no top 5 clientes, formado por SANTANDER, SANEAMENTO, MRS, RECUPERA, MERCADO LIVRE, que juntos somam R$ 8,29 M. A liderança de SANTANDER, com 12,4% desse bloco, sinaliza um nível relevante de concentração comercial e mantém a diversificação da carteira como agenda prioritária."
    ],
    "meta": {
      "mode": "template",
      "provider": null
    }
  },
  "cost_subtitle": "+10,9% vs 2025"
}